Metadata-Version: 1.1
Name: neurophox
Version: 0.1.0a4
Summary: A simulation framework for unitary neural networks and photonic devices
Home-page: https://github.com/solgaardlab/neurophox
Author: Sunil Pai
Author-email: sunilpai@stanford.edu
License: MIT
Platform: UNKNOWN
Classifier: Development Status :: 3 - Alpha
Classifier: Intended Audience :: Developers
Classifier: Natural Language :: English
Classifier: License :: OSI Approved :: MIT License
Classifier: Programming Language :: Python
Classifier: Programming Language :: Python :: 3
Classifier: Programming Language :: Python :: 3.6
Classifier: Programming Language :: Python :: 3.7
